aputil/__init__.py
aputil/fc.py
aputil/helper.py
aputil/tcursor.py
aputil/typings.py
aputil/xcursor.py
aputil/toolbox/__init__.py
aputil/toolbox/parameters.py
APUtil-0.4.6.dist-info/LICENSE
APUtil-0.4.6.dist-info/METADATA
APUtil-0.4.6.dist-info/WHEEL
APUtil-0.4.6.dist-info/top_level.txt
APUtil-0.4.6.dist-info/RECORD
