Metadata-Version: 2.1
Name: APUtil
Version: 0.4.6
Summary: Collection of arcpy helper classes and functions
Home-page: https://github.com/moosetraveller/aputil
Author: Thomas Zuberbuehler
Author-email: thomas.zuberbuehler@gmail.com
License: MIT
Keywords: arcpy,util,arcgis,esri,cursor,gis,arcgis-pro
Classifier: License :: OSI Approved :: MIT License
Classifier: Programming Language :: Python
Classifier: Programming Language :: Python :: 3.9
Classifier: Intended Audience :: Developers
Classifier: Intended Audience :: Education
Classifier: Natural Language :: English
Classifier: Development Status :: 3 - Alpha
Classifier: Operating System :: Microsoft :: Windows
Classifier: Operating System :: Microsoft :: Windows :: Windows 10
Classifier: Operating System :: Microsoft :: Windows :: Windows 11
Classifier: Topic :: Scientific/Engineering
Classifier: Topic :: Scientific/Engineering :: GIS
Classifier: Topic :: Software Development :: Libraries
Classifier: Topic :: Software Development :: Libraries :: Python Modules
Classifier: Topic :: Utilities
License-File: LICENSE
